create_project_directories/__init__.py
create_project_directories/main.py
xgh_create_project_directories-0.0.0.dist-info/LICENSE
xgh_create_project_directories-0.0.0.dist-info/METADATA
xgh_create_project_directories-0.0.0.dist-info/WHEEL
xgh_create_project_directories-0.0.0.dist-info/entry_points.txt
xgh_create_project_directories-0.0.0.dist-info/top_level.txt
xgh_create_project_directories-0.0.0.dist-info/RECORD
