Metadata-Version: 2.1
Name: xgh-create-project-directories
Version: 0.0.0
Summary: 生成工程目录结构
Home-page: UNKNOWN
Author: xgh
License: UNKNOWN
Platform: UNKNOWN
License-File: LICENSE
